octavia_dashboard/__init__.py
octavia_dashboard/karma.conf.js
octavia_dashboard/post_install.sh
octavia_dashboard/sdk_connection.py
octavia_dashboard/version.py
octavia_dashboard/api/__init__.py
octavia_dashboard/api/rest/__init__.py
octavia_dashboard/api/rest/barbican.py
octavia_dashboard/api/rest/lbaasv2.py
octavia_dashboard/conf/.gitkeep
octavia_dashboard/dashboards/__init__.py
octavia_dashboard/dashboards/project/__init__.py
octavia_dashboard/dashboards/project/load_balancer/__init__.py
octavia_dashboard/dashboards/project/load_balancer/panel.py
octavia_dashboard/dashboards/project/load_balancer/urls.py
octavia_dashboard/dashboards/project/load_balancer/views.py
octavia_dashboard/dashboards/project/load_balancer/templates/load_balancer/index.html
octavia_dashboard/enabled/_1482_project_load_balancer_panel.py
octavia_dashboard/enabled/__init__.py
octavia_dashboard/local_settings.d/_1499_load_balancer_settings.py
octavia_dashboard/locale/de/LC_MESSAGES/django.po
octavia_dashboard/locale/de/LC_MESSAGES/djangojs.po
octavia_dashboard/locale/en_AU/LC_MESSAGES/django.po
octavia_dashboard/locale/en_GB/LC_MESSAGES/django.po
octavia_dashboard/locale/en_GB/LC_MESSAGES/djangojs.po
octavia_dashboard/locale/es/LC_MESSAGES/django.po
octavia_dashboard/locale/fr/LC_MESSAGES/django.po
octavia_dashboard/locale/id/LC_MESSAGES/django.po
octavia_dashboard/locale/id/LC_MESSAGES/djangojs.po
octavia_dashboard/locale/ja/LC_MESSAGES/django.po
octavia_dashboard/locale/ja/LC_MESSAGES/djangojs.po
octavia_dashboard/locale/ko_KR/LC_MESSAGES/django.po
octavia_dashboard/locale/ko_KR/LC_MESSAGES/djangojs.po
octavia_dashboard/locale/pt_BR/LC_MESSAGES/django.po
octavia_dashboard/locale/ru/LC_MESSAGES/django.po
octavia_dashboard/locale/ru/LC_MESSAGES/djangojs.po
octavia_dashboard/locale/zh_Hans/LC_MESSAGES/django.po
octavia_dashboard/locale/zh_Hans/LC_MESSAGES/djangojs.po
octavia_dashboard/locale/zh_Hant/LC_MESSAGES/django.po
octavia_dashboard/locale/zh_Hant/LC_MESSAGES/djangojs.po
octavia_dashboard-16.0.0.dist-info/AUTHORS
octavia_dashboard-16.0.0.dist-info/LICENSE
octavia_dashboard-16.0.0.dist-info/METADATA
octavia_dashboard-16.0.0.dist-info/WHEEL
octavia_dashboard-16.0.0.dist-info/pbr.json
octavia_dashboard-16.0.0.dist-info/top_level.txt
octavia_dashboard-16.0.0.dist-info/RECORD
