Metadata-Version: 2.1
Name: octavia-dashboard
Version: 16.0.0
Summary: Horizon panels for Octavia
Home-page: https://docs.openstack.org/octavia-dashboard/latest/
Author: OpenStack
Author-email: openstack-discuss@lists.openstack.org
Classifier: Environment :: OpenStack
Classifier: Intended Audience :: Information Technology
Classifier: Intended Audience :: System Administrators
Classifier: License :: OSI Approved :: Apache Software License
Classifier: Operating System :: POSIX :: Linux
Classifier: Programming Language :: Python
Classifier: Programming Language :: Python :: Implementation :: CPython
Classifier: Programming Language :: Python :: 3 :: Only
Classifier: Programming Language :: Python :: 3
Classifier: Programming Language :: Python :: 3.10
Classifier: Programming Language :: Python :: 3.11
Classifier: Programming Language :: Python :: 3.12
Requires-Python: >=3.10
License-File: LICENSE
License-File: AUTHORS
Requires-Dist: horizon >=17.1.0
Requires-Dist: Babel >=2.3.4
Requires-Dist: openstacksdk >=0.53.0
Requires-Dist: pbr >=2.0.0
Requires-Dist: python-keystoneclient >=3.22.0
